tw_experimentation/__init__.py
tw_experimentation/bayes/__init__.py
tw_experimentation/bayes/bayes_model.py
tw_experimentation/bayes/bayes_params.py
tw_experimentation/bayes/bayes_test.py
tw_experimentation/bayes/numpyro_monkeypatch.py
tw_experimentation/checker.py
tw_experimentation/constants.py
tw_experimentation/data_generation.py
tw_experimentation/plotting/__init__.py
tw_experimentation/plotting/monitoring_plots.py
tw_experimentation/result_generator.py
tw_experimentation/segmentation_frequentist.py
tw_experimentation/setuper.py
tw_experimentation/statistical_tests.py
tw_experimentation/streamlit/.streamlit/config.toml
tw_experimentation/streamlit/Main.py
tw_experimentation/streamlit/__init__.py
tw_experimentation/streamlit/pages/1_Data Loading.py
tw_experimentation/streamlit/pages/2_Experiment Design.py
tw_experimentation/streamlit/pages/3_Monitoring.py
tw_experimentation/streamlit/pages/4_Experiment Evaluation.py
tw_experimentation/streamlit/pages/5_Experiment Evaluation Bayesian.py
tw_experimentation/streamlit/pages/__init__.py
tw_experimentation/streamlit/pages_wrap/__init__.py
tw_experimentation/streamlit/pages_wrap/page1_Data_Loading.py
tw_experimentation/streamlit/pages_wrap/page2_Experiment_Design.py
tw_experimentation/streamlit/pages_wrap/page3_Monitoring.py
tw_experimentation/streamlit/pages_wrap/page4_Experiment_Evaluation.py
tw_experimentation/streamlit/pages_wrap/page5_Experiment_Evaluation_Bayesian.py
tw_experimentation/streamlit/run_streamlit_app_entry_point.py
tw_experimentation/streamlit/streamlit_utils.py
tw_experimentation/synthetic_data.py
tw_experimentation/tester.py
tw_experimentation/utils.py
tw_experimentation/variance_reduction/__init__.py
tw_experimentation/variance_reduction/cupac.py
tw_experimentation/variance_reduction/cuped.py
tw_experimentation/variance_reduction/diff_in_means.py
tw_experimentation/variance_reduction/doubly_robust.py
tw_experimentation/variance_reduction/evaluation_pipeline.py
tw_experimentation-0.1.2.4.dist-info/LICENSE.txt
tw_experimentation-0.1.2.4.dist-info/METADATA
tw_experimentation-0.1.2.4.dist-info/WHEEL
tw_experimentation-0.1.2.4.dist-info/entry_points.txt
tw_experimentation-0.1.2.4.dist-info/RECORD
