Metadata-Version: 2.1
Name: tw-experimentation
Version: 0.1.2.4
Summary: Wise AB platform
Author: Wise
Requires-Python: >=3.9, !=2.7.*, !=3.0.*, !=3.1.*, !=3.2.*, !=3.3.*, !=3.4.*, !=3.5.*, !=3.6.*, !=3.7.*, !=3.8.*, !=3.10.*, !=3.11.*, !=3.12.*
Classifier: Programming Language :: Python :: 3
Classifier: Programming Language :: Python :: 3.9
Requires-Dist: conda-lock (>=2.4.1,<3.0.0)
Requires-Dist: ipywidgets (>=8.1,<9.0)
Requires-Dist: jax (>=0.4.16,<0.5.0)
Requires-Dist: jaxlib (>=0.4.14,<0.5.0)
Requires-Dist: jupyter (>=1.0,<2.0)
Requires-Dist: kaleido (==0.2.1)
Requires-Dist: matplotlib (>=3.8,<4.0)
Requires-Dist: numba (>=0.58.1,<0.59.0)
Requires-Dist: numpy (==1.23.5)
Requires-Dist: numpyro (==0.13.2)
Requires-Dist: pandas (<1.5.3)
Requires-Dist: plotly (>=5.17,<6.0)
Requires-Dist: pytest (>=7.4,<8.0)
Requires-Dist: scikit-learn (>=1.1.3,<2.0.0)
Requires-Dist: scipy (==1.11.3)
Requires-Dist: seaborn (>=0.13.0,<0.14.0)
Requires-Dist: snowflake-sqlalchemy (>=1.5,<2.0)
Requires-Dist: sqlalchemy (>=1.4,<2.0)
Requires-Dist: statsmodels (>=0.13,<0.14)
Requires-Dist: streamlit (>=1.28,<2.0)
Requires-Dist: wise-pizza (>=0.2.0)
